benchmarks/fixed_num_problems/gen_scripts.py
benchmarks/fixed_num_problems/rand_seq.py
benchmarks/fixed_time/fixed_time_exp.py
benchmarks/fixed_time/gen_scripts.py
benchmarks/fixed_time/param_problem.py
qfactor/__init__.py
qfactor/optimize.py
qfactor/tensors.py
qfactor/utils.py
qfactor/gates/__init__.py
qfactor/gates/cnot.py
qfactor/gates/gate.py
qfactor/gates/rx.py
qfactor/gates/ry.py
qfactor/gates/rz.py
qfactor/gates/xx.py
qfactor-1.0.1.dist-info/LICENSE.txt
qfactor-1.0.1.dist-info/METADATA
qfactor-1.0.1.dist-info/WHEEL
qfactor-1.0.1.dist-info/top_level.txt
qfactor-1.0.1.dist-info/RECORD
