Metadata-Version: 2.1
Name: qfactor
Version: 1.0.1
Summary: Quantum Fast Circuit Optimizer
Home-page: https://github.com/edyounis/qfactor
Author: Ed Younis
Author-email: edyounis@lbl.gov
License: UNKNOWN
Project-URL: Bug Tracker, https://github.com/edyounis/qfactor/issues
Project-URL: Source Code, https://github.com/edyounis/qfactor
Keywords: quantum circuit optimization optimizer
Platform: UNKNOWN
Classifier: Development Status :: 5 - Production/Stable
Classifier: Environment :: Console
Classifier: Intended Audience :: Developers
Classifier: Intended Audience :: Science/Research
Classifier: Operating System :: OS Independent
Classifier: Programming Language :: Python :: 3 :: Only
Classifier: Programming Language :: Python :: 3.5
Classifier: Programming Language :: Python :: 3.6
Classifier: Programming Language :: Python :: 3.7
Classifier: Topic :: Scientific/Engineering
Classifier: Topic :: Scientific/Engineering :: Mathematics
Classifier: Topic :: Scientific/Engineering :: Physics
Classifier: Topic :: Software Development :: Compilers
Requires-Python: >=3.5, <4
Requires-Dist: numpy (>=1.16.6)
Requires-Dist: scipy (>=1.4.1)
